pathway_abstract_classifier/__init__.py
pathway_abstract_classifier/app.py
pathway_abstract_classifier/pathway_abstract_classifier.py
pathway_abstract_classifier-0.2.2.dist-info/LICENSE
pathway_abstract_classifier-0.2.2.dist-info/WHEEL
pathway_abstract_classifier-0.2.2.dist-info/METADATA
pathway_abstract_classifier-0.2.2.dist-info/RECORD
