Metadata-Version: 2.1
Name: pathway-abstract-classifier
Version: 0.2.2
Summary: A tool to classify articles containing biological pathway information
Home-page: https://github.com/PathwayCommons/pathway-abstract-classifier
License: MIT
Author: Biofactoid
Author-email: support@biofactoid.org
Maintainer: Biofactoid
Maintainer-email: support@biofactoid.org
Requires-Python: >=3.8,<3.10
Classifier: Environment :: Console
Classifier: Intended Audience :: Science/Research
Classifier: License :: OSI Approved :: MIT License
Classifier: License :: OSI Approved :: MIT No Attribution License (MIT-0)
Classifier: Operating System :: OS Independent
Classifier: Programming Language :: Python :: 3
Classifier: Programming Language :: Python :: 3.10
Classifier: Programming Language :: Python :: 3.8
Classifier: Programming Language :: Python :: 3.9
Classifier: Topic :: Scientific/Engineering :: Artificial Intelligence
Requires-Dist: cached-path (>=1.1.1,<2.0.0)
Requires-Dist: ktrain (==0.30.0)
Requires-Dist: pydantic (>=1.9.0,<2.0.0)
Requires-Dist: tensorflow (==2.8.0)
Project-URL: Repository, https://github.com/PathwayCommons/pathway-abstract-classifier
